dted/__init__.py
dted/__main__.py
dted/definitions.py
dted/errors.py
dted/latlon.py
dted/records/__init__.py
dted/records/_casts.py
dted/records/acc.py
dted/records/dsi.py
dted/records/uhl.py
dted/tile.py
dted/tileset.py
dted-1.3.0.dist-info/LICENSE
dted-1.3.0.dist-info/METADATA
dted-1.3.0.dist-info/WHEEL
dted-1.3.0.dist-info/entry_points.txt
dted-1.3.0.dist-info/RECORD
