Metadata-Version: 2.3
Name: dted
Version: 1.3.0
Summary: Parser for DTED data.
License: MIT
Keywords: DTED,SRTM,terrain,elevation
Author: Ben Bonenfant
Author-email: bonenfan5ben@gmail.com
Requires-Python: >=3.10,<4.0
Classifier: Development Status :: 5 - Production/Stable
Classifier: Intended Audience :: Science/Research
Classifier: License :: OSI Approved :: MIT License
Classifier: Operating System :: OS Independent
Classifier: Programming Language :: Python :: 3
Classifier: Programming Language :: Python :: 3.10
Classifier: Programming Language :: Python :: 3.11
Classifier: Programming Language :: Python :: 3.12
Classifier: Programming Language :: Python :: 3.13
Classifier: Topic :: Scientific/Engineering :: Atmospheric Science
Classifier: Topic :: Scientific/Engineering :: GIS
Requires-Dist: numpy (>=1.22)
Project-URL: Homepage, https://github.com/bbonenfant/dted
Project-URL: Repository, https://github.com/bbonenfant/dted
